rs_distances-1.0.0.dist-info/METADATA
rs_distances-1.0.0.dist-info/WHEEL
rs_distances/__init__.py
rs_distances/rs_distances.cp310-win_amd64.pyd
rs_distances-1.0.0.dist-info/RECORD
