Metadata-Version: 2.1
Name: rs-distances
Version: 1.0.0
Classifier: Programming Language :: Rust
Classifier: License :: OSI Approved :: MIT License
Classifier: Development Status :: 4 - Beta
Classifier: Intended Audience :: Developers
Classifier: Intended Audience :: Science/Research
Classifier: Operating System :: OS Independent
Summary: A Python module implemented in Rust for efficient calculations
Author-email: Flynn OConnell <flynnoconnell@gmail.com>
License: MIT
Requires-Python: >=3.7
Project-URL: homepage, https://github.com/NeuroPyPy/rs-distances
Project-URL: repository, https://github.com/NeuroPyPy/rs-distances
Project-URL: documentation, http://www-users.med.cornell.edu/~jdvicto/metricdf.html#algorithm
